setup.py
Products/__init__.py
Products.BastionBanking.egg-info/PKG-INFO
Products.BastionBanking.egg-info/SOURCES.txt
Products.BastionBanking.egg-info/dependency_links.txt
Products.BastionBanking.egg-info/entry_points.txt
Products.BastionBanking.egg-info/namespace_packages.txt
Products.BastionBanking.egg-info/not-zip-safe
Products.BastionBanking.egg-info/requires.txt
Products.BastionBanking.egg-info/top_level.txt
Products/BastionBanking/Archetypes.py
Products/BastionBanking/BastionBankLog.py
Products/BastionBanking/BastionBankService.py
Products/BastionBanking/BastionMerchantService.py
Products/BastionBanking/BastionPayee.py
Products/BastionBanking/BastionPayment.py
Products/BastionBanking/BastionTradeable.py
Products/BastionBanking/ConnectionMgr.py
Products/BastionBanking/Converters.py
Products/BastionBanking/CurrencyIndex.py
Products/BastionBanking/Exceptions.py
Products/BastionBanking/Permissions.py
Products/BastionBanking/PortalContent.py
Products/BastionBanking/ZCreditCard.py
Products/BastionBanking/ZCurrency.py
Products/BastionBanking/ZReturnCode.py
Products/BastionBanking/__init__.py
Products/BastionBanking/config.py
Products/BastionBanking/creditcard.py
Products/BastionBanking/currency.py
Products/BastionBanking/returncode.py
Products/BastionBanking/Banks/__init__.py
Products/BastionBanking/Banks/ManualPayment/ManualPayment.py
Products/BastionBanking/Banks/ManualPayment/__init__.py
Products/BastionBanking/Extensions/Install.py
Products/BastionBanking/Extensions/__init__.py
Products/BastionBanking/Merchants/__init__.py
Products/BastionBanking/Merchants/BNZ/ZBNZ.py
Products/BastionBanking/Merchants/BNZ/__init__.py
Products/BastionBanking/Merchants/BNZ/bnz.py
Products/BastionBanking/Merchants/BNZ/setup.py
Products/BastionBanking/Merchants/BarclayCard/ZBarclayCard.py
Products/BastionBanking/Merchants/BarclayCard/__init__.py
Products/BastionBanking/Merchants/PayPal/ZPayPal.py
Products/BastionBanking/Merchants/PayPal/__init__.py
Products/BastionBanking/Merchants/PayPalDirect/ZPayPalDirect.py
Products/BastionBanking/Merchants/PayPalDirect/__init__.py
Products/BastionBanking/Merchants/PinPayments/ZPinPayments.py
Products/BastionBanking/Merchants/PinPayments/__init__.py
Products/BastionBanking/Merchants/StGeorge/ZStGeorge.py
Products/BastionBanking/Merchants/StGeorge/__init__.py
Products/BastionBanking/Merchants/StGeorge/setup.py
