Metadata-Version: 1.1
Name: Products.BastionBanking
Version: 4.2.3
Summary: Zope/Plone monetary products.
Home-page: http://www.last-bastion.net/forge/bastionbanking
Author: Alan Milligan
Author-email: alan.milligan@last-bastion.net
License: GPL
Keywords: BastionBanking
Platform: UNKNOWN
Classifier: Framework :: Plone
Classifier: Programming Language :: Python
Classifier: Development Status :: 5 - Production/Stable
Classifier: License :: OSI Approved :: GNU General Public License (GPL)
